polychron/Config.py
polychron/GUIApp.py
polychron/__init__.py
polychron/__main__.py
polychron/_version.py
polychron/entrypoint.py
polychron/interfaces.py
polychron/mcmc.py
polychron/util.py
polychron/models/AddContextModel.py
polychron/models/DatafilePreviewModel.py
polychron/models/GroupRelationship.py
polychron/models/InterpolatedRCDCalibrationCurve.py
polychron/models/MCMCData.py
polychron/models/Model.py
polychron/models/Project.py
polychron/models/ProjectSelection.py
polychron/models/ProjectsDirectory.py
polychron/models/RemoveContextModel.py
polychron/models/RemoveStratigraphicRelationshipModel.py
polychron/models/__init__.py
polychron/presenters/AddContextPresenter.py
polychron/presenters/CalibrateModelSelectPresenter.py
polychron/presenters/DatafilePreviewPresenter.py
polychron/presenters/DatingResultsPresenter.py
polychron/presenters/FramePresenter.py
polychron/presenters/MCMCProgressPresenter.py
polychron/presenters/ManageGroupRelationshipsPresenter.py
polychron/presenters/ManageIntrusiveOrResidualContextsPresenter.py
polychron/presenters/ModelCreatePresenter.py
polychron/presenters/ModelPresenter.py
polychron/presenters/ModelSelectPresenter.py
polychron/presenters/PopupPresenter.py
polychron/presenters/ProjectCreatePresenter.py
polychron/presenters/ProjectSelectPresenter.py
polychron/presenters/ProjectSelectProcessPopupPresenter.py
polychron/presenters/ProjectWelcomePresenter.py
polychron/presenters/RemoveContextPresenter.py
polychron/presenters/RemoveStratigraphicRelationshipPresenter.py
polychron/presenters/ResidualOrIntrusivePresenter.py
polychron/presenters/SelectCalibrationCurvePresenter.py
polychron/presenters/SplashPresenter.py
polychron/presenters/__init__.py
polychron/resources/intcal20_interpolated.csv
polychron/resources/logo.png
polychron/resources/marine20_interpolated.csv
polychron/resources/shcal20_interpolated.csv
polychron/views/AddContextView.py
polychron/views/CalibrateModelSelectView.py
polychron/views/DatafilePreviewView.py
polychron-0.2.1.dist-info/METADATA
polychron-0.2.1.dist-info/WHEEL
polychron-0.2.1.dist-info/entry_points.txt
polychron-0.2.1.dist-info/licenses/LICENSE
polychron-0.2.1.dist-info/RECORD
