Metadata-Version: 2.4
Name: polychron
Version: 0.2.1
Summary: Analysis and archiving of archaeological dating evidence
Project-URL: Documentation, https://bryonymoody.github.io/PolyChron
Project-URL: Repository, https://github.com/bryonymoody/PolyChron
Project-URL: Issues, https://github.com/bryonymoody/PolyChron/issues
Author-email: Bryony Moody <bryony.moody@sheffield.ac.uk>, Peter Heywood <p.heywood@sheffield.ac.uk>, Shreyan Ghosh <shreyanghosh27@gmail.com>
Maintainer-email: Bryony Moody <bryony.moody@sheffield.ac.uk>
License-Expression: GPL-3.0-only
License-File: LICENSE
Keywords: chronology,statistics
Classifier: Development Status :: 4 - Beta
Classifier: Intended Audience :: Science/Research
Classifier: Operating System :: MacOS
Classifier: Operating System :: Microsoft :: Windows
Classifier: Operating System :: POSIX :: Linux
Classifier: Programming Language :: Python :: 3
Classifier: Programming Language :: Python :: 3.9
Classifier: Programming Language :: Python :: 3.10
Classifier: Programming Language :: Python :: 3.11
Classifier: Programming Language :: Python :: 3.12
Classifier: Programming Language :: Python :: 3.13
Classifier: Topic :: Scientific/Engineering
Classifier: Topic :: Scientific/Engineering :: Information Analysis
Classifier: Topic :: Scientific/Engineering :: Mathematics
Classifier: Topic :: Sociology :: History
Requires-Python: >=3.9
Requires-Dist: graphviz
Requires-Dist: lxml>=6
Requires-Dist: matplotlib
Requires-Dist: networkx>=2; python_version < '3.10'
Requires-Dist: networkx>=3.4; python_version >= '3.10'
Requires-Dist: numpy>=2
Requires-Dist: packaging
Requires-Dist: pandas>=2
Requires-Dist: pydot<4
Requires-Dist: pyyaml
Requires-Dist: ttkthemes
Provides-Extra: dev
Requires-Dist: ruff; extra == 'dev'
Provides-Extra: doc
Requires-Dist: markdown-callouts; extra == 'doc'
Requires-Dist: mkdocs-gen-files; extra == 'doc'
Requires-Dist: mkdocs-literate-nav; extra == 'doc'
Requires-Dist: mkdocs-macros-plugin; extra == 'doc'
Requires-Dist: mkdocs-material>=9.5.0; extra == 'doc'
Requires-Dist: mkdocs-section-index; extra == 'doc'
Requires-Dist: mkdocstrings[python]>=0.18; extra == 'doc'
Requires-Dist: tomli; (python_version < '3.11') and extra == 'doc'
Provides-Extra: test
Requires-Dist: pytest>=6.0; extra == 'test'
